[
    {
        "date": "2025-07-04",
        "apmc_name": "हरभरा",
        "variety": "लोकल",
        "unit": "क्विंटल",
        "min_price": "78",
        "max_price": "5400",
        "modal_price": "5910",
        "avg_price": "5800"
    },
    {
        "date": "2025-07-04",
        "apmc_name": "तूर",
        "variety": "लाल",
        "unit": "क्विंटल",
        "min_price": "468",
        "max_price": "5500",
        "modal_price": "6800",
        "avg_price": "6216"
    },
    {
        "date": "2025-07-03",
        "apmc_name": "हरभरा",
        "variety": "लोकल",
        "unit": "क्विंटल",
        "min_price": "43",
        "max_price": "5000",
        "modal_price": "5765",
        "avg_price": "5765"
    },
    {
        "date": "2025-07-03",
        "apmc_name": "मका",
        "variety": "हायब्रीड",
        "unit": "क्विंटल",
        "min_price": "8",
        "max_price": "2035",
        "modal_price": "2035",
        "avg_price": "2035"
    },
    {
        "date": "2025-07-03",
        "apmc_name": "तूर",
        "variety": "लाल",
        "unit": "क्विंटल",
        "min_price": "702",
        "max_price": "5600",
        "modal_price": "6770",
        "avg_price": "6297"
    },
    {
        "date": "2025-07-03",
        "apmc_name": "ज्वारी",
        "variety": "पांढरी",
        "unit": "क्विंटल",
        "min_price": "23",
        "max_price": "2140",
        "modal_price": "2690",
        "avg_price": "2472"
    },
    {
        "date": "2025-07-03",
        "apmc_name": "गहू",
        "variety": "२१८९",
        "unit": "क्विंटल",
        "min_price": "5",
        "max_price": "2435",
        "modal_price": "2435",
        "avg_price": "2435"
    },
    {
        "date": "2025-07-02",
        "apmc_name": "बाजरी",
        "variety": "महिको",
        "unit": "क्विंटल",
        "min_price": "1",
        "max_price": "1900",
        "modal_price": "1900",
        "avg_price": "1900"
    },
    {
        "date": "2025-07-02",
        "apmc_name": "हरभरा",
        "variety": "लोकल",
        "unit": "क्विंटल",
        "min_price": "11",
        "max_price": "5000",
        "modal_price": "5500",
        "avg_price": "5288"
    },
    {
        "date": "2025-07-02",
        "apmc_name": "मका",
        "variety": "हायब्रीड",
        "unit": "क्विंटल",
        "min_price": "14",
        "max_price": "1800",
        "modal_price": "2240",
        "avg_price": "2013"
    },
    {
        "date": "2025-07-02",
        "apmc_name": "तूर",
        "variety": "लाल",
        "unit": "क्विंटल",
        "min_price": "1368",
        "max_price": "500",
        "modal_price": "6800",
        "avg_price": "6266"
    },
    {
        "date": "2025-07-02",
        "apmc_name": "ज्वारी",
        "variety": "पांढरी",
        "unit": "क्विंटल",
        "min_price": "61",
        "max_price": "1950",
        "modal_price": "3015",
        "avg_price": "2480"
    },
    {
        "date": "2025-07-02",
        "apmc_name": "गहू",
        "variety": "२१८९",
        "unit": "क्विंटल",
        "min_price": "10",
        "max_price": "2435",
        "modal_price": "2700",
        "avg_price": "2527"
    },
    {
        "date": "2025-07-01",
        "apmc_name": "हरभरा",
        "variety": "लोकल",
        "unit": "क्विंटल",
        "min_price": "20",
        "max_price": "5600",
        "modal_price": "5750",
        "avg_price": "5750"
    },
    {
        "date": "2025-07-01",
        "apmc_name": "मका",
        "variety": "हायब्रीड",
        "unit": "क्विंटल",
        "min_price": "9",
        "max_price": "2170",
        "modal_price": "2225",
        "avg_price": "2198"
    },
    {
        "date": "2025-07-01",
        "apmc_name": "तूर",
        "variety": "लाल",
        "unit": "क्विंटल",
        "min_price": "1248",
        "max_price": "5000",
        "modal_price": "6850",
        "avg_price": "6309"
    },
    {
        "date": "2025-07-01",
        "apmc_name": "ज्वारी",
        "variety": "पांढरी",
        "unit": "क्विंटल",
        "min_price": "77",
        "max_price": "2025",
        "modal_price": "2770",
        "avg_price": "2324"
    },
    {
        "date": "2025-07-01",
        "apmc_name": "गहू",
        "variety": "२१८९",
        "unit": "क्विंटल",
        "min_price": "24",
        "max_price": "2445",
        "modal_price": "2500",
        "avg_price": "2467"
    },
    {
        "date": "2025-06-30",
        "apmc_name": "हरभरा",
        "variety": "लोकल",
        "unit": "क्विंटल",
        "min_price": "21",
        "max_price": "5605",
        "modal_price": "5770",
        "avg_price": "5735"
    },
    {
        "date": "2025-06-30",
        "apmc_name": "मका",
        "variety": "हायब्रीड",
        "unit": "क्विंटल",
        "min_price": "14",
        "max_price": "2150",
        "modal_price": "2260",
        "avg_price": "2203"
    },
    {
        "date": "2025-06-30",
        "apmc_name": "तूर",
        "variety": "लाल",
        "unit": "क्विंटल",
        "min_price": "1075",
        "max_price": "5500",
        "modal_price": "6885",
        "avg_price": "6418"
    },
    {
        "date": "2025-06-30",
        "apmc_name": "ज्वारी",
        "variety": "पांढरी",
        "unit": "क्विंटल",
        "min_price": "75",
        "max_price": "1335",
        "modal_price": "2980",
        "avg_price": "2459"
    },
    {
        "date": "2025-06-30",
        "apmc_name": "गहू",
        "variety": "२१८९",
        "unit": "क्विंटल",
        "min_price": "83",
        "max_price": "2440",
        "modal_price": "2735",
        "avg_price": "2496"
    },
    {
        "date": "2025-06-28",
        "apmc_name": "उडीद",
        "variety": "काळा",
        "unit": "क्विंटल",
        "min_price": "15",
        "max_price": "6000",
        "modal_price": "6450",
        "avg_price": "6225"
    },
    {
        "date": "2025-06-28",
        "apmc_name": "हरभरा",
        "variety": "लोकल",
        "unit": "क्विंटल",
        "min_price": "8",
        "max_price": "5200",
        "modal_price": "5650",
        "avg_price": "5650"
    },
    {
        "date": "2025-06-28",
        "apmc_name": "तूर",
        "variety": "लाल",
        "unit": "क्विंटल",
        "min_price": "577",
        "max_price": "5200",
        "modal_price": "6750",
        "avg_price": "6275"
    },
    {
        "date": "2025-06-28",
        "apmc_name": "ज्वारी",
        "variety": "पांढरी",
        "unit": "क्विंटल",
        "min_price": "37",
        "max_price": "2000",
        "modal_price": "2845",
        "avg_price": "2568"
    },
    {
        "date": "2025-06-28",
        "apmc_name": "गहू",
        "variety": "२१८९",
        "unit": "क्विंटल",
        "min_price": "17",
        "max_price": "2450",
        "modal_price": "2990",
        "avg_price": "2713"
    },
    {
        "date": "2025-06-28",
        "apmc_name": "खपली",
        "variety": "---",
        "unit": "क्विंटल",
        "min_price": "4",
        "max_price": "4400",
        "modal_price": "4400",
        "avg_price": "4400"
    },
    {
        "date": "2025-06-27",
        "apmc_name": "हरभरा",
        "variety": "लोकल",
        "unit": "क्विंटल",
        "min_price": "11",
        "max_price": "5400",
        "modal_price": "5400",
        "avg_price": "5400"
    },
    {
        "date": "2025-06-27",
        "apmc_name": "तूर",
        "variety": "लाल",
        "unit": "क्विंटल",
        "min_price": "635",
        "max_price": "5200",
        "modal_price": "6780",
        "avg_price": "6203"
    },
    {
        "date": "2025-06-27",
        "apmc_name": "ज्वारी",
        "variety": "पांढरी",
        "unit": "क्विंटल",
        "min_price": "21",
        "max_price": "1920",
        "modal_price": "2305",
        "avg_price": "2188"
    },
    {
        "date": "2025-06-27",
        "apmc_name": "गहू",
        "variety": "२१८९",
        "unit": "क्विंटल",
        "min_price": "1",
        "max_price": "2430",
        "modal_price": "2430",
        "avg_price": "2430"
    },
    {
        "date": "2025-06-27",
        "apmc_name": "खपली",
        "variety": "---",
        "unit": "क्विंटल",
        "min_price": "3",
        "max_price": "4005",
        "modal_price": "4005",
        "avg_price": "4005"
    }
]