[
    {
        "date": "2025-07-03",
        "apmc_name": "पुणे",
        "variety": "लोकल",
        "unit": "क्विंटल",
        "min_price": "3",
        "max_price": "5000",
        "modal_price": "5300",
        "avg_price": "5150"
    },
    {
        "date": "2025-07-02",
        "apmc_name": "पुणे",
        "variety": "लोकल",
        "unit": "क्विंटल",
        "min_price": "2",
        "max_price": "5300",
        "modal_price": "5600",
        "avg_price": "5420"
    },
    {
        "date": "2025-07-01",
        "apmc_name": "पुणे",
        "variety": "लोकल",
        "unit": "क्विंटल",
        "min_price": "3",
        "max_price": "5500",
        "modal_price": "5800",
        "avg_price": "5650"
    },
    {
        "date": "2025-06-30",
        "apmc_name": "पुणे",
        "variety": "लोकल",
        "unit": "क्विंटल",
        "min_price": "4",
        "max_price": "5400",
        "modal_price": "5800",
        "avg_price": "5600"
    },
    {
        "date": "2025-06-28",
        "apmc_name": "पुणे",
        "variety": "लोकल",
        "unit": "क्विंटल",
        "min_price": "3",
        "max_price": "5400",
        "modal_price": "5700",
        "avg_price": "5550"
    },
    {
        "date": "2025-06-27",
        "apmc_name": "पुणे",
        "variety": "लोकल",
        "unit": "क्विंटल",
        "min_price": "2",
        "max_price": "5300",
        "modal_price": "5600",
        "avg_price": "5450"
    },
    {
        "date": "2025-06-26",
        "apmc_name": "पुणे",
        "variety": "लोकल",
        "unit": "क्विंटल",
        "min_price": "3",
        "max_price": "5400",
        "modal_price": "5700",
        "avg_price": "5550"
    }
]